framecraft/__init__.py
framecraft/framecraft.py
framecraft-0.2.6.dist-info/METADATA
framecraft-0.2.6.dist-info/WHEEL
framecraft-0.2.6.dist-info/top_level.txt
framecraft-0.2.6.dist-info/RECORD
